deutschland/dip_bundestag/__init__.py
deutschland/dip_bundestag/api/__init__.py
deutschland/dip_bundestag/api/aktivitten_api.py
deutschland/dip_bundestag/api/drucksachen_api.py
deutschland/dip_bundestag/api/personenstammdaten_api.py
deutschland/dip_bundestag/api/plenarprotokolle_api.py
deutschland/dip_bundestag/api/vorgangspositionen_api.py
deutschland/dip_bundestag/api/vorgnge_api.py
deutschland/dip_bundestag/api_client.py
deutschland/dip_bundestag/apis/__init__.py
deutschland/dip_bundestag/configuration.py
deutschland/dip_bundestag/exceptions.py
deutschland/dip_bundestag/model/__init__.py
deutschland/dip_bundestag/model/aktivitaet.py
deutschland/dip_bundestag/model/aktivitaet_anzeige.py
deutschland/dip_bundestag/model/aktivitaet_list_response.py
deutschland/dip_bundestag/model/aktivitaet_list_response_all_of.py
deutschland/dip_bundestag/model/beschlussfassung.py
deutschland/dip_bundestag/model/bundesland.py
deutschland/dip_bundestag/model/deskriptor.py
deutschland/dip_bundestag/model/dokument_text_base.py
deutschland/dip_bundestag/model/drucksache.py
deutschland/dip_bundestag/model/drucksache_autoren_anzeige_inner.py
deutschland/dip_bundestag/model/drucksache_list_response.py
deutschland/dip_bundestag/model/drucksache_list_response_all_of.py
deutschland/dip_bundestag/model/drucksache_text.py
deutschland/dip_bundestag/model/drucksache_text_list_response.py
deutschland/dip_bundestag/model/drucksache_text_list_response_all_of.py
deutschland/dip_bundestag/model/fundstelle.py
deutschland/dip_bundestag/model/get_vorgang404_response.py
deutschland/dip_bundestag/model/get_vorgang_list400_response.py
deutschland/dip_bundestag/model/get_vorgang_list401_response.py
deutschland/dip_bundestag/model/inkrafttreten.py
deutschland/dip_bundestag/model/list_response_base.py
deutschland/dip_bundestag/model/person.py
deutschland/dip_bundestag/model/person_list_response.py
deutschland/dip_bundestag/model/person_list_response_all_of.py
deutschland/dip_bundestag/model/person_role.py
de_dip_bundestag-0.1.1.dist-info/METADATA
de_dip_bundestag-0.1.1.dist-info/WHEEL
de_dip_bundestag-0.1.1.dist-info/RECORD
